graph_games_proto/__init__.py
graph_games_proto/all_types.py
graph_games_proto/fns.py
graph_games_proto/llm.md
graph_games_proto/main.py
graph_games_proto/state.py
graph_games_proto-0.3.2914.dist-info/METADATA
graph_games_proto-0.3.2914.dist-info/WHEEL
graph_games_proto-0.3.2914.dist-info/top_level.txt
graph_games_proto-0.3.2914.dist-info/RECORD
