Metadata-Version: 2.4
Name: graph_games_proto
Version: 0.3.2914
Requires-Dist: multipledispatch==1.0.0
Requires-Dist: pyrsistent==0.20.0
Requires-Dist: numpy==2.2.4
Dynamic: requires-dist
